opendistillery/__init__.py
opendistillery/api/__init__.py
opendistillery/api/enterprise_api.py
opendistillery/api/enterprise_endpoints.py
opendistillery/api/server.py
opendistillery/cli/__init__.py
opendistillery/cli/commands.py
opendistillery/cli/next_gen_cli.py
opendistillery/cli/prompting_commands.py
opendistillery/core/__init__.py
opendistillery/core/compound_system.py
opendistillery/core/model_hub.py
opendistillery/integrations/__init__.py
opendistillery/integrations/dspy_integration.py
opendistillery/integrations/grok_integration.py
opendistillery/integrations/multi_provider_api.py
opendistillery/integrations/openai_agents.py
opendistillery/integrations/openai_integration.py
opendistillery/integrations/salesforce_integration.py
opendistillery/research/__init__.py
opendistillery/research/experiment_runner.py
opendistillery/research/techniques/__init__.py
opendistillery/research/techniques/graph_of_thoughts.py
opendistillery/research/techniques/next_gen_prompting.py
opendistillery/research/techniques/prompting_strategies.py
opendistillery/research/techniques/react_engine.py
opendistillery/research/techniques/self_consistency.py
opendistillery/research/techniques/tree_of_thoughts.py
opendistillery/research/techniques/prompting_plugins/constitutional_ai.py
opendistillery/research/techniques/prompting_plugins/example_registrations.py
opendistillery/research/techniques/prompting_plugins/gradient_prompt_search.py
opendistillery/research/techniques/prompting_plugins/meta_prompting.py
opendistillery/research/techniques/prompting_plugins/meta_prompting_v2.py
opendistillery/research/techniques/prompting_plugins/registry.py
opendistillery-2.0.3.dist-info/METADATA
opendistillery-2.0.3.dist-info/WHEEL
opendistillery-2.0.3.dist-info/entry_points.txt
opendistillery-2.0.3.dist-info/licenses/LICENSE
opendistillery-2.0.3.dist-info/RECORD
