Metadata-Version: 2.4
Name: opendistillery
Version: 2.0.3
Summary: Advanced Compound AI Systems for Enterprise Workflow Transformation
Project-URL: Homepage, https://github.com/nikjois/OpenDistillery
Project-URL: Documentation, https://docs.opendistillery.ai
Project-URL: Repository, https://github.com/nikjois/OpenDistillery.git
Project-URL: Issues, https://github.com/nikjois/OpenDistillery/issues
Project-URL: Changelog, https://github.com/nikjois/OpenDistillery/blob/main/CHANGELOG.md
Author-email: Nik Jois <nikjois@llamasearch.ai>
Maintainer-email: Nik Jois <nikjois@llamasearch.ai>
License:                                  Apache License
License-File: LICENSE
Keywords: ai,anthropic,artificial-intelligence,automation,compound-ai,enterprise,grok,llm,machine-learning,multi-agent,openai,orchestration,workflow
Classifier: Development Status :: 5 - Production/Stable
Classifier: Intended Audience :: Developers
Classifier: License :: OSI Approved :: MIT License
Classifier: Operating System :: OS Independent
Classifier: Programming Language :: Python :: 3
Classifier: Programming Language :: Python :: 3.9
Classifier: Programming Language :: Python :: 3.10
Classifier: Programming Language :: Python :: 3.11
Classifier: Programming Language :: Python :: 3.12
Classifier: Topic :: Scientific/Engineering :: Artificial Intelligence
Classifier: Topic :: Software Development :: Libraries :: Python Modules
Classifier: Topic :: System :: Distributed Computing
Requires-Python: >=3.9
Requires-Dist: aiofiles>=23.2.1
Requires-Dist: alembic>=1.13.0
Requires-Dist: anthropic>=0.7.8
Requires-Dist: asyncpg>=0.29.0
Requires-Dist: celery>=5.3.4
Requires-Dist: click>=8.1.7
Requires-Dist: cryptography>=41.0.7
Requires-Dist: fastapi>=0.104.1
Requires-Dist: httpx>=0.25.2
Requires-Dist: numpy>=1.24.3
Requires-Dist: openai>=1.3.7
Requires-Dist: pandas>=2.1.4
Requires-Dist: passlib[bcrypt]>=1.7.4
Requires-Dist: pillow>=10.1.0
Requires-Dist: prometheus-client>=0.19.0
Requires-Dist: pydantic>=2.5.0
Requires-Dist: pyjwt>=2.8.0
Requires-Dist: pyotp>=2.9.0
Requires-Dist: python-dotenv>=1.0.0
Requires-Dist: python-jose[cryptography]>=3.3.0
Requires-Dist: python-multipart>=0.0.6
Requires-Dist: qrcode>=7.4.2
Requires-Dist: redis>=5.0.1
Requires-Dist: requests>=2.31.0
Requires-Dist: rich>=13.7.0
Requires-Dist: scikit-learn>=1.3.2
Requires-Dist: sqlalchemy>=2.0.23
Requires-Dist: structlog>=23.2.0
Requires-Dist: typer>=0.9.0
Requires-Dist: uvicorn[standard]>=0.24.0
Provides-Extra: dev
Requires-Dist: black>=23.11.0; extra == 'dev'
Requires-Dist: build>=1.0.3; extra == 'dev'
Requires-Dist: flake8>=6.1.0; extra == 'dev'
Requires-Dist: isort>=5.12.0; extra == 'dev'
Requires-Dist: mypy>=1.7.1; extra == 'dev'
Requires-Dist: pre-commit>=3.6.0; extra == 'dev'
Requires-Dist: pytest-asyncio>=0.21.1; extra == 'dev'
Requires-Dist: pytest-cov>=4.1.0; extra == 'dev'
Requires-Dist: pytest>=7.4.3; extra == 'dev'
Requires-Dist: twine>=4.0.2; extra == 'dev'
Provides-Extra: docs
Requires-Dist: mkdocs-material>=9.4.8; extra == 'docs'
Requires-Dist: mkdocs-mermaid2-plugin>=1.1.1; extra == 'docs'
Requires-Dist: mkdocs>=1.5.3; extra == 'docs'
